{"cameraMode":{"drawMode":0,"name":"Shaded","section":"Shading Mode"},"sceneLighting":false,"audioPlay":false,"sceneViewState":{"m_AlwaysRefresh":false,"showFog":true,"showSkybox":false,"showFlares":true,"showImageEffects":true,"showParticleSystems":true,"showVisualEffectGraphs":true,"m_FxEnabled":true},"in2DMode":false,"pivot":{"x":0.0,"y":-0.003017100505530834,"z":4.656612873077393e-10},"rotation":{"x":0.31479281187057497,"y":0.33489301800727847,"z":-0.1197284460067749,"w":0.8800398111343384},"size":11.718694686889649,"orthographic":false}